odoo/addons/ssi_project_operating_unit/README.rst
odoo/addons/ssi_project_operating_unit/__init__.py
odoo/addons/ssi_project_operating_unit/__manifest__.py
odoo/addons/ssi_project_operating_unit/i18n/ssi_project_operating_unit.pot
odoo/addons/ssi_project_operating_unit/models/__init__.py
odoo/addons/ssi_project_operating_unit/models/project_project.py
odoo/addons/ssi_project_operating_unit/models/project_task.py
odoo/addons/ssi_project_operating_unit/security/ir_rule/project_project.xml
odoo/addons/ssi_project_operating_unit/security/ir_rule/project_task.xml
odoo/addons/ssi_project_operating_unit/security/res_group/project_project.xml
odoo/addons/ssi_project_operating_unit/security/res_group/project_task.xml
odoo/addons/ssi_project_operating_unit/static/description/icon.png
odoo/addons/ssi_project_operating_unit/views/project_project_views.xml
odoo/addons/ssi_project_operating_unit/views/project_task_views.xml
odoo14_addon_ssi_project_operating_unit-14.0.1.1.0.dist-info/METADATA
odoo14_addon_ssi_project_operating_unit-14.0.1.1.0.dist-info/WHEEL
odoo14_addon_ssi_project_operating_unit-14.0.1.1.0.dist-info/top_level.txt
odoo14_addon_ssi_project_operating_unit-14.0.1.1.0.dist-info/RECORD
